fleetchain/__init__.py
fleetchain/chain.py
fleetchain/user.py
fleetchain-0.1.1.dist-info/LICENSE
fleetchain-0.1.1.dist-info/METADATA
fleetchain-0.1.1.dist-info/WHEEL
fleetchain-0.1.1.dist-info/RECORD
